rcon_fake/__init__.py
rcon_fake/rcon_fake.py
rcon_fake-0.1.dist-info/METADATA
rcon_fake-0.1.dist-info/WHEEL
rcon_fake-0.1.dist-info/top_level.txt
rcon_fake-0.1.dist-info/RECORD
