Metadata-Version: 2.1
Name: rcon-fake
Version: 0.1
Summary: The RCON-Fake library allows you to accept user commands using the RCON protocol.
Home-page: https://github.com/local1ka/rcon-fake.git
Author: local1ka
Author-email: alexarst@mail.ru
License: UNKNOWN
Project-URL: GitHub, https://github.com/local1ka/rcon-fake.git
Platform: UNKNOWN
Requires-Python: >=3.6
